ytsubs/__init__.py
ytsubs/__main__.py
ytsubs/base_scraper.py
ytsubs/cli.py
ytsubs/db_schema.py
ytsubs/debug_scrape.py
ytsubs/generate_feed.py
ytsubs/schema.sql
ytsubs/scrape_channel_stats.py
ytsubs/scrape_videos.py
ytsubs/static_template.html
ytsubs-0.1.1.dist-info/licenses/LICENSE
ytsubs-0.1.1.dist-info/METADATA
ytsubs-0.1.1.dist-info/WHEEL
ytsubs-0.1.1.dist-info/entry_points.txt
ytsubs-0.1.1.dist-info/top_level.txt
ytsubs-0.1.1.dist-info/RECORD
