Metadata-Version: 2.4
Name: ytsubs
Version: 0.1.1
Summary: Personal YouTube subscriptions scraper that ranks videos and generates a static feed.
Author-email: Shayne Sweeney <79330+shayne@users.noreply.github.com>
License: MIT
Project-URL: Homepage, https://github.com/shayne/ytsubs
Project-URL: Repository, https://github.com/shayne/ytsubs
Project-URL: Issues, https://github.com/shayne/ytsubs/issues
Keywords: youtube,subscriptions,scraper,playwright,feed,ranking
Classifier: Development Status :: 3 - Alpha
Classifier: Environment :: Console
Classifier: Intended Audience :: End Users/Desktop
Classifier: License :: OSI Approved :: MIT License
Classifier: Programming Language :: Python :: 3
Classifier: Programming Language :: Python :: 3 :: Only
Classifier: Programming Language :: Python :: 3.12
Classifier: Programming Language :: Python :: 3.13
Classifier: Programming Language :: Python :: 3.14
Classifier: Topic :: Internet :: WWW/HTTP
Classifier: Topic :: Utilities
Requires-Python: >=3.12
License-File: LICENSE
Requires-Dist: playwright>=1.51.0
Requires-Dist: rich>=14.2.0
Requires-Dist: textual>=6.8.0
Dynamic: license-file
